{"nodes": [{"id": "confirmsignup_email", "label": "Confirm Signup Email Template", "file_type": "code", "source_file": "supabase/email-templates/confirm-signup.html", "source_location": null, "source_url": null, "captured_at": null, "author": null, "contributor": null}, {"id": "confirmsignup_branding", "label": "RBO Brand Identity in Email", "file_type": "rationale", "source_file": "supabase/email-templates/confirm-signup.html", "source_location": null, "source_url": null, "captured_at": null, "author": null, "contributor": null}, {"id": "confirmsignup_confirmation_url", "label": "Supabase ConfirmationURL Template Variable", "file_type": "code", "source_file": "supabase/email-templates/confirm-signup.html", "source_location": "line 39", "source_url": null, "captured_at": null, "author": null, "contributor": null}], "edges": [{"source": "confirmsignup_email", "target": "concept_supabase_auth", "relation": "implements", "confidence": "EXTRACTED", "confidence_score": 1.0, "source_file": "supabase/email-templates/confirm-signup.html", "source_location": null, "weight": 1.0}, {"source": "confirmsignup_email", "target": "confirmsignup_confirmation_url", "relation": "references", "confidence": "EXTRACTED", "confidence_score": 1.0, "source_file": "supabase/email-templates/confirm-signup.html", "source_location": "line 39", "weight": 1.0}, {"source": "confirmsignup_email", "target": "confirmsignup_branding", "relation": "implements", "confidence": "EXTRACTED", "confidence_score": 1.0, "source_file": "supabase/email-templates/confirm-signup.html", "source_location": null, "weight": 1.0}, {"source": "confirmsignup_email", "target": "concept_rbo_backoffice", "relation": "references", "confidence": "EXTRACTED", "confidence_score": 1.0, "source_file": "supabase/email-templates/confirm-signup.html", "source_location": "line 15", "weight": 1.0}], "hyperedges": []}